labelimgobb2DOTA_converter/__init__.py
labelimgobb2DOTA_converter/cli/__init__.py
labelimgobb2DOTA_converter/cli/main.py
labelimgobb2DOTA_converter/core/__init__.py
labelimgobb2DOTA_converter/core/converter.py
labelimgobb2DOTA_converter/core/obb_utils.py
labelimgobb2DOTA_converter/gui/__init__.py
labelimgobb2DOTA_converter/gui/dialogs.py
labelimgobb2DOTA_converter/gui/main_window.py
labelimgobb2DOTA_converter/utils/__init__.py
labelimgobb2DOTA_converter/utils/dataset_utils.py
labelimgobb2DOTA_converter/utils/file_utils.py
labelimgobb2dota_converter-0.1.3.dist-info/licenses/LICENSE
labelimgobb2dota_converter-0.1.3.dist-info/METADATA
labelimgobb2dota_converter-0.1.3.dist-info/WHEEL
labelimgobb2dota_converter-0.1.3.dist-info/entry_points.txt
labelimgobb2dota_converter-0.1.3.dist-info/top_level.txt
labelimgobb2dota_converter-0.1.3.dist-info/RECORD
