Metadata-Version: 2.4
Name: labelimgobb2DOTA-converter
Version: 0.1.3
Summary: 一个用于转换DOTA格式和labelimgOBB格式的工具
Author-email: Blake Zhu <2112304124@mail2.gdut.edu.cn>
Maintainer-email: Blake Zhu <2112304124@mail2.gdut.edu.cn>
License: MIT
Project-URL: Homepage, https://github.com/BIANG-qilie/LabelimgOBB2YOLOOBB
Project-URL: Documentation, https://github.com/BIANG-qilie/LabelimgOBB2YOLOOBB#readme
Project-URL: Repository, https://github.com/BIANG-qilie/LabelimgOBB2YOLOOBB.git
Project-URL: Bug Tracker, https://github.com/BIANG-qilie/LabelimgOBB2YOLOOBB/issues
Keywords: yolo,obb,object-detection,computer-vision,annotation-tool
Classifier: Development Status :: 4 - Beta
Classifier: Intended Audience :: Developers
Classifier: Intended Audience :: Science/Research
Classifier: Operating System :: OS Independent
Classifier: Programming Language :: Python :: 3
Classifier: Programming Language :: Python :: 3.6
Classifier: Programming Language :: Python :: 3.7
Classifier: Programming Language :: Python :: 3.8
Classifier: Programming Language :: Python :: 3.9
Classifier: Programming Language :: Python :: 3.10
Classifier: Programming Language :: Python :: 3.11
Classifier: Topic :: Scientific/Engineering :: Artificial Intelligence
Classifier: Topic :: Software Development :: Libraries :: Python Modules
Requires-Python: >=3.6
License-File: LICENSE
Requires-Dist: numpy>=1.19.0
Requires-Dist: pillow>=8.0.0
Provides-Extra: dev
Requires-Dist: pytest>=6.0.0; extra == "dev"
Requires-Dist: pytest-cov>=2.0.0; extra == "dev"
Requires-Dist: black>=21.0.0; extra == "dev"
Requires-Dist: flake8>=3.8.0; extra == "dev"
Requires-Dist: mypy>=0.812; extra == "dev"
Requires-Dist: pre-commit>=2.15.0; extra == "dev"
Provides-Extra: gui
Requires-Dist: pillow>=8.0.0; extra == "gui"
Provides-Extra: test
Requires-Dist: pytest>=6.0.0; extra == "test"
Requires-Dist: pytest-cov>=2.0.0; extra == "test"
Requires-Dist: pytest-mock>=3.6.0; extra == "test"
Dynamic: license-file
